LICENSE
MANIFEST.in
README.md
setup.py
calaccess_campaign_browser/__init__.py
calaccess_campaign_browser/admin.py
calaccess_campaign_browser/api.py
calaccess_campaign_browser/apps.py
calaccess_campaign_browser/managers.py
calaccess_campaign_browser/models.py
calaccess_campaign_browser/tests.py
calaccess_campaign_browser/urls.py
calaccess_campaign_browser/management/__init__.py
calaccess_campaign_browser/management/commands/__init__.py
calaccess_campaign_browser/management/commands/buildcalaccesscampaignbrowser.py
calaccess_campaign_browser/management/commands/dropcalaccesscampaignbrowser.py
calaccess_campaign_browser/management/commands/exportcalaccesscampaignbrowser.py
calaccess_campaign_browser/management/commands/flushcalaccesscampaignbrowser.py
calaccess_campaign_browser/management/commands/loadcalaccesscampaigncontributions.py
calaccess_campaign_browser/management/commands/loadcalaccesscampaignexpenditures.py
calaccess_campaign_browser/management/commands/loadcalaccesscampaignfilers.py
calaccess_campaign_browser/management/commands/loadcalaccesscampaignfilings.py
calaccess_campaign_browser/management/commands/loadcalaccesscampaignsummaries.py
calaccess_campaign_browser/management/commands/scrapecalaccesscampaigncandidates.py
calaccess_campaign_browser/management/commands/scrapecalaccesscampaignpropositions.py
calaccess_campaign_browser/static/calaccess_campaign_browser/css/bootstrap.min.css
calaccess_campaign_browser/static/calaccess_campaign_browser/css/font-awesome.min.css
calaccess_campaign_browser/static/calaccess_campaign_browser/css/home.css
calaccess_campaign_browser/static/calaccess_campaign_browser/css/main.css
calaccess_campaign_browser/static/calaccess_campaign_browser/fonts/FontAwesome.otf
calaccess_campaign_browser/static/calaccess_campaign_browser/fonts/fontawesome-webfont.eot
calaccess_campaign_browser/static/calaccess_campaign_browser/fonts/fontawesome-webfont.svg
django_calaccess_campaign_browser.egg-info/PKG-INFO
django_calaccess_campaign_browser.egg-info/SOURCES.txt
django_calaccess_campaign_browser.egg-info/dependency_links.txt
django_calaccess_campaign_browser.egg-info/not-zip-safe
django_calaccess_campaign_browser.egg-info/pbr.json
django_calaccess_campaign_browser.egg-info/requires.txt
django_calaccess_campaign_browser.egg-info/top_level.txt