Metadata-Version: 1.0
Name: django-calaccess-campaign-browser
Version: 0.1.1
Summary: A Django app to refine and investigate campaign finance data drawn from the California Secretary of State’s CAL-ACCESS database. This is a work in progress. Its analysis should be considered as provisional until it is further tested and debugged.
Home-page: http://django-calaccess-campaign-browser.californiacivicdata.org
Author: California Civic Data Coalition
Author-email: awilliams@cironline.org
License: MIT
Platform: UNKNOWN
